CONTRIBUTING.rst
HISTORY.rst
LICENSE
MANIFEST.in
README.rst
setup.cfg
setup.py
docs/Makefile
docs/conf.py
docs/contributing.rst
docs/history.rst
docs/index.rst
docs/installation.rst
docs/jontools.rst
docs/make.bat
docs/modules.rst
docs/readme.rst
docs/usage.rst
docs/_build/html/_static/ajax-loader.gif
docs/_build/html/_static/comment-bright.png
docs/_build/html/_static/comment-close.png
docs/_build/html/_static/comment.png
docs/_build/html/_static/down-pressed.png
docs/_build/html/_static/down.png
docs/_build/html/_static/file.png
docs/_build/html/_static/minus.png
docs/_build/html/_static/plus.png
docs/_build/html/_static/up-pressed.png
docs/_build/html/_static/up.png
jontools/__init__.py
jontools/cli.py
jontools/jontools.py
jontools.egg-info/PKG-INFO
jontools.egg-info/SOURCES.txt
jontools.egg-info/dependency_links.txt
jontools.egg-info/entry_points.txt
jontools.egg-info/not-zip-safe
jontools.egg-info/requires.txt
jontools.egg-info/top_level.txt
tests/test_jontools.py