Metadata-Version: 1.1
Name: jontools
Version: 0.1.0
Summary: Jon Tools Duh
Home-page: https://github.com/jyoun009/jontools
Author: Jonathan Young
Author-email: jyoun009@gmail.com
License: MIT license
Keywords: jontools
Platform: UNKNOWN
Classifier: Development Status :: 2 - Pre-Alpha
Classifier: Intended Audience :: Developers
Classifier: License :: OSI Approved :: MIT License
Classifier: Natural Language :: English
Classifier: Programming Language :: Python :: 2
Classifier: Programming Language :: Python :: 2.7
Classifier: Programming Language :: Python :: 3
Classifier: Programming Language :: Python :: 3.4
Classifier: Programming Language :: Python :: 3.5
Classifier: Programming Language :: Python :: 3.6
Classifier: Programming Language :: Python :: 3.7
